easy_env_var/__init__.py
easy_env_var/py.typed
easy_env_var-1.2.0.dist-info/METADATA
easy_env_var-1.2.0.dist-info/WHEEL
easy_env_var-1.2.0.dist-info/licenses/LICENSE
easy_env_var-1.2.0.dist-info/RECORD
