Metadata-Version: 2.3
Name: easy_env_var
Version: 1.2.0
Summary: Simple util to get environment variables in the right data type.
Project-URL: Homepage, https://github.com/Geekeno/easy-env-var
Project-URL: Documentation, https://github.com/Geekeno/easy-env-var
Project-URL: Source, https://github.com/Geekeno/easy-env-var
Project-URL: Tracker, https://github.com/Geekeno/easy-env-var/issues
Author-email: Geekeno <dev@geekeno.com>
License: MIT License
License-File: LICENSE
Classifier: Development Status :: 5 - Production/Stable
Classifier: Intended Audience :: Developers
Classifier: License :: OSI Approved :: MIT License
Classifier: Natural Language :: English
Classifier: Operating System :: OS Independent
Classifier: Programming Language :: Python :: 3.7
Classifier: Programming Language :: Python :: 3.8
Classifier: Programming Language :: Python :: 3.9
Classifier: Programming Language :: Python :: 3.10
Classifier: Programming Language :: Python :: 3.11
Classifier: Programming Language :: Python :: 3.12
Classifier: Programming Language :: Python :: 3.13
Classifier: Topic :: Utilities
Classifier: Typing :: Typed
Requires-Python: >=3.7
